{
  "example_spell":{
    "display_name": "example spell",
    "spell_level": 0,
    "classes": ["wizard","cleric"],
    "cast_time": "1 action",
    "range": "120 ft.",
    "components": "S,V,M (something something)",
    "duration": "Instantaneous",
    "description": "This spell does XYZ, on a hit roll 200d6 psychic damage due to the pain of coding this bot",
    "higher_levels_description" : "At higher levels blah blah",
    "cantrip_damage_scaling": {
      "5": "2d6",
      "7": "3d6"
    },
    "upcasting_data": {
      "scaling_amount": "1d6",
      "additional_levels_required" : "1"
    }
  }
}
